Workbook

Sheet Итог
A1: Парк на месте болота, Архангельск — сводка сметы
A2: Синие числа — исходные допущения, их можно менять. Остальное считается формулами.
A4: Допущения
A5: Непредвиденные, % от прямых | B5: 0.12
A6: Проектирование, % от прямых | B6: 0.06
A7: Технадзор, % от прямых | B7: 0.03
A8: Экспертиза, % от прямых | B8: 0.008
A9: Инженерные изыскания, ₽ | B9: 4200000
A10: НДС | B10: 0.22
A11: Включить ресторан «Тоня» в бюджет (1 — да, 0 — нет) | B11: 0
A14: Разделы | B14: Прямые затраты, ₽
A15: 1. Подготовка территории | B15: =Ведомость!F7 -> 8082670.5
A16: 2. Водоём из болота: земляные работы и гидротехника | B16: =Ведомость!F27 -> 58214436
A17: 3. Дороги, площадки, настилы | B17: =Ведомость!F40 -> 64668805
A18: 4. Здания и сооружения | B18: =Ведомость!F51 -> 104872000
A19: 5. Детская, спортивная и собачья зоны | B19: =Ведомость!F65 -> 18555750
A20: 6. Озеленение | B20: =Ведомость!F89 -> 60630636
A21: 7. Ливневая система и биоинженерия | B21: =Ведомость!F96 -> 12242050
A22: 8. Инженерные сети и освещение | B22: =Ведомость!F107 -> 27989035
A23: 9. Малые архитектурные формы и навигация | B23: =Ведомость!F120 -> 13509000
A24: 10. Ресторан «Тоня» (по умолчанию — за счёт инвестора-арендатора) | B24: =Ведомость!F127 -> 127228000
A26: Прямые затраты парка | B26: =SUM(B15:B23)+B24*$B$11 -> 368764383
A27: Непредвиденные | B27: =B26*$B$5 -> 44251726
A28: Проектирование | B28: =B26*$B$6 -> 22125863
A29: Технадзор | B29: =B26*$B$7 -> 11062931
A30: Экспертиза | B30: =B26*$B$8 -> 2950115.1
A31: Изыскания | B31: =$B$9 -> 4200000
A32: Итого без НДС | B32: =SUM(B26:B31) -> 4.5335502e+08
A33: НДС | B33: =B32*$B$10 -> 99738104
A34: ИТОГО С НДС | B34: =B32+B33 -> 5.5309312e+08
A36: Ресторан отдельно, с резервами и НДС | B36: =B24*(1+$B$5+$B$6+$B$7+$B$8)*(1+$B$10) -> 1.8905572e+08
A37: Итог в млн ₽ | B37: =B34/1000000 -> 553.09312

Sheet Ведомость
A1: № | B1: Наименование работ и затрат | C1: Ед. | D1: Количество | E1: Цена за ед., ₽ | F1: Сумма, ₽ | G1: Примечание
A2: 1 | B2: Подготовка территории
A3: 1.1 | B3: Ограждение стройплощадки (профнастил H=2 м) | C3: м | D3: 1306.6 | E3: 1150 | F3: =D3*E3 -> 1502590 | G3: периметр участка
A4: 1.2 | B4: Расчистка: срезка кустарника и мелколесья, вывоз порубочных остатков и мусора | C4: м² | D4: 78194.5 | E4: 38 | F4: =D4*E4 -> 2971391 | G4: вся суша участка
A5: 1.3 | B5: Геодезическая разбивка и вынос осей в натуру | C5: м² | D5: 101965.5 | E5: 9 | F5: =D5*E5 -> 917689.5 | G5: вся площадь участка
A6: 1.4 | B6: Временные технологические проезды из дорожных плит (аренда, укладка, демонтаж) | C6: м² | D6: 2340 | E6: 1150 | F6: =D6*E6 -> 2691000 | G6: 520 м × 4,5 м
B7: Итого по разделу | F7: =SUM(F3:F6) -> 8082670.5
A9: 2 | B9: Водоём из болота: земляные работы и гидротехника
A10: 2.1 | B10: Водопонижение и перемычки: организация сухих карт на акватории | C10: м² | D10: 23771 | E10: 95 | F10: =D10*E10 -> 2258245 | G10: площадь воды по проекту
A11: 2.2 | B11: Разработка торфа и сапропеля в акватории экскаватором с матов (глубина от 0,30 м до проектной) | C11: м³ | D11: 26873.8 | E11: 640 | F11: =D11*E11 -> 17199232 | G11: V = ∫(h проект − 0,30 м) dA
A12: 2.3 | B12: Перемещение торфа на карты подсушки (≤ 250 м), укладка слоями | C12: м³ | D12: 26873.8 | E12: 310 | F12: =D12*E12 -> 8330878
A13: 2.4 | B13: Отсыпка из торфо-грунтовой смеси: берма, холм башни, подъём отметок зон, откосы берегов | C13: м³ | D13: 19184.9 | E13: 540 | F13: =D13*E13 -> 10359846 | G13: берма 4 511 + холм 4 222 + подъём 9 525 + откосы 927
A14: 2.5 | B14: Привозной минеральный грунт (дефицит после усадки торфа) | C14: м³ | D14: 373.2 | E14: 980 | F14: =D14*E14 -> 365736 | G14: усадка торфа при подсушке принята 30 %
A15: 2.6 | B15: Профилирование дна и откосов 1:4, шельф 0,45 м | C15: м² | D15: 23771 | E15: 85 | F15: =D15*E15 -> 2020535 | G15: тонкая планировка под водой
A16: 2.7 | B16: Каскад из 3 ступеней (ЖБ + облицовка природным камнем), перепад 0,9 м | C16: ст. | D16: 3 | E16: 1150000 | F16: =D16*E16 -> 3450000 | G16: канал 8 м шириной
A17: 2.8 | B17: Укрепление уреза кокосовыми биоваликами Ø30 см | C17: м | D17: 1287 | E17: 1250 | F17: =D17*E17 -> 1608750 | G17: береговая линия, включая полуостров
A18: 2.9 | B18: Кокосовый биомат на откосах (ширина 2,2 м) | C18: м² | D18: 2831.5 | E18: 410 | F18: =D18*E18 -> 1160915
A19: 2.10 | B19: Каменная наброска у пирсов и каскада | C19: м³ | D19: 150 | E19: 6800 | F19: =D19*E19 -> 1020000
A20: 2.11 | B20: Водовыпуск и регулятор уровня (переливной колодец, труба Ø600 в существующий водоотвод) | C20: компл. | D20: 1 | E20: 1850000 | F20: =D20*E20 -> 1850000
A21: 2.12 | B21: Рециркуляционная насосная станция 30 л/с | C21: компл. | D21: 1 | E21: 2350000 | F21: =D21*E21 -> 2350000 | G21: полный оборот воды ≈ 13 сут
A22: 2.13 | B22: Напорный трубопровод ПНД Ø250 | C22: м | D22: 176.2 | E22: 4600 | F22: =D22*E22 -> 810520 | G22: пруд 2 → верховье пруда 1
A23: 2.14 | B23: Донная аэрация (компрессор + диффузоры), пруды 1 и 2 | C23: компл. | D23: 2 | E23: 1550000 | F23: =D23*E23 -> 3100000
A24: 2.15 | B24: Литораль: водные и прибрежные растения (60 % шельфа, 7 шт/м²) | C24: шт. | D24: 14759.8 | E24: 105 | F24: =D24*E24 -> 1549779 | G24: тростник, рогоз, аир, ирис болотный, сабельник, калужница
A25: 2.16 | B25: Растения глубокой воды: кувшинка белая, кубышка | C25: шт. | D25: 400 | E25: 650 | F25: =D25*E25 -> 260000
A26: 2.17 | B26: Биологическая подготовка водоёма: зоопланктон, моллюски-фильтраторы, фитофаги | C26: компл. | D26: 1 | E26: 520000 | F26: =D26*E26 -> 520000
B27: Итого по разделу | F27: =SUM(F10:F26) -> 58214436
A29: 3 | B29: Дороги, площадки, настилы
A30: 3.1 | B30: Главные аллеи 3,0 м: цветной асфальтобетон на основании (геосетка, щебень 25 см, ПГС) | C30: м² | D30: 3442.8 | E30: 5200 | F30: =D30*E30 -> 17902560 | G30: длина 1 107 м
A31: 3.2 | B31: Второстепенные дорожки 2,0–2,5 м: каменная мелочь с вяжущим на геотекстиле | C31: м² | D31: 2113 | E31: 3100 | F31: =D31*E31 -> 6550300 | G31: длина 923 м
A32: 3.3 | B32: Беговая дорожка 3,0 м: EPDM-покрытие по асфальту | C32: м² | D32: 903.5 | E32: 6200 | F32: =D32*E32 -> 5601700 | G32: длина 264 м
A33: 3.4 | B33: Входная площадь: гранитная плитка | C33: м² | D33: 709.5 | E33: 11200 | F33: =D33*E33 -> 7946400
A34: 3.5 | B34: Деревянные настилы на винтовых сваях (лиственница): мостки, пирсы, мостик каскада, йога-настил | C34: м² | D34: 598 | E34: 26000 | F34: =D34*E34 -> 15548000
A35: 3.6 | B35: Перила настилов (лиственница) | C35: м | D35: 237.6 | E35: 8200 | F35: =D35*E35 -> 1948320 | G35: с двух сторон
A36: 3.7 | B36: Бортовой камень вдоль главных аллей и площади | C36: м | D36: 2418.5 | E36: 1450 | F36: =D36*E36 -> 3506825
A37: 3.8 | B37: Покрытие служебного двора: щебень по геотекстилю | C37: м² | D37: 1298 | E37: 1850 | F37: =D37*E37 -> 2401300
A38: 3.9 | B38: Хозяйственный проезд к ресторану (асфальтобетон по щебню, совмещён с пожарным) | C38: м² | D38: 530 | E38: 5200 | F38: =D38*E38 -> 2756000 | G38: 66 м от проспекта + двор
A39: 3.10 | B39: Подходы к павильонам и ресторану (плитка) | C39: м² | D39: 118 | E39: 4300 | F39: =D39*E39 -> 507400
B40: Итого по разделу | F40: =SUM(F30:F39) -> 64668805
A42: 4 | B42: Здания и сооружения
A43: 4.1 | B43: Смотровая башня H = 18 м (дерево/сталь, 2 площадки), на холме 7 м | C43: шт. | D43: 1 | E43: 15800000 | F43: =D43*E43 -> 15800000 | G43: фундамент — винтовые сваи через насыпь
A44: 4.2 | B44: Входной павильон-навес (с кассой и информацией) | C44: м² | D44: 120 | E44: 98000 | F44: =D44*E44 -> 11760000
A45: 4.3 | B45: Павильон у воды | C45: м² | D45: 64 | E45: 62000 | F45: =D45*E45 -> 3968000
A46: 4.4 | B46: Кафе-киоски | C46: м² | D46: 40 | E46: 130000 | F46: =D46*E46 -> 5200000 | G46: 2 шт.
A47: 4.5 | B47: Павильоны-туалеты «Северная летопись» 8,4 × 4,8 м: клеть с повалом, высокая кровля, 4 кабины (1 универсальная для МГН), тёплые | C47: шт. | D47: 4 | E47: 8600000 | F47: =D47*E47 -> 34400000 | G47: каркас и брус, утепление 200 мм, электроотопление, резьба и медальоны
A48: 4.6 | B48: Хоз. блок и склад | C48: м² | D48: 84 | E48: 78000 | F48: =D48*E48 -> 6552000
A49: 4.7 | B49: Мастерская «Поморская ладья» 10 × 6 м, высота до 3,2 м (деревянные рёбра, кровля) | C49: м² | D49: 60 | E49: 145000 | F49: =D49*E49 -> 8700000 | G49: кровля и опоры по расчёту на снег
A50: 4.8 | B50: Крытые галереи с двускатной кровлей, подкосами и резными деталями (4 шт.) | C50: м | D50: 201 | E50: 92000 | F50: =D50*E50 -> 18492000 | G50: 52 + 50 + 50 + 49 м
B51: Итого по разделу | F51: =SUM(F43:F50) -> 104872000
A53: 5 | B53: Детская, спортивная и собачья зоны
A54: 5.1 | B54: Игровой комплекс «Башни–мост» (лиственница) | C54: компл. | D54: 1 | E54: 2950000 | F54: =D54*E54 -> 2950000
A55: 5.2 | B55: Канатный городок | C55: компл. | D55: 1 | E55: 1850000 | F55: =D55*E55 -> 1850000
A56: 5.3 | B56: Качели-гнёзда и балансиры | C56: компл. | D56: 1 | E56: 740000 | F56: =D56*E56 -> 740000
A57: 5.4 | B57: Песочный двор | C57: компл. | D57: 1 | E57: 420000 | F57: =D57*E57 -> 420000
A58: 5.5 | B58: Сплэш-пад с рециркуляцией воды | C58: м² | D58: 144 | E58: 28000 | F58: =D58*E58 -> 4032000
A59: 5.6 | B59: Резиновое покрытие EPDM игровых площадок | C59: м² | D59: 384 | E59: 5400 | F59: =D59*E59 -> 2073600
A60: 5.7 | B60: Теневой парус | C60: шт. | D60: 1 | E60: 640000 | F60: =D60*E60 -> 640000
A61: 5.8 | B61: Воркаут и уличные тренажёры | C61: компл. | D61: 1 | E61: 2350000 | F61: =D61*E61 -> 2350000
A62: 5.9 | B62: Волейбольная площадка (песок, сетка, ограждение) | C62: шт. | D62: 1 | E62: 1150000 | F62: =D62*E62 -> 1150000
A63: 5.10 | B63: Площадка для собак: ограждение 2 м | C63: м | D63: 241.5 | E63: 4100 | F63: =D63*E63 -> 990150
A64: 5.11 | B64: Площадка для собак: оборудование и поилки | C64: компл. | D64: 1 | E64: 1360000 | F64: =D64*E64 -> 1360000
B65: Итого по разделу | F65: =SUM(F54:F64) -> 18555750
A67: 6 | B67: Озеленение
A68: 6.1 | B68: Берёза повислая и пушистая (Betula pendula, B. pubescens) | C68: шт. | D68: 295 | E68: 7800 | F68: =D68*E68 -> 2301000 | G68: посадка с комом, в т.ч. яма и подвязка
A69: 6.2 | B69: Яблоня ягодная (Malus baccata), h 2,5–3 м | C69: шт. | D69: 162 | E69: 6300 | F69: =D69*E69 -> 1020600 | G69: посадка с комом, в т.ч. яма и подвязка
A70: 6.3 | B70: Сосна обыкновенная (Pinus sylvestris), h 3 м | C70: шт. | D70: 162 | E70: 12500 | F70: =D70*E70 -> 2025000 | G70: посадка с комом, в т.ч. яма и подвязка
A71: 6.4 | B71: Ель европейская и сибирская (Picea abies, P. obovata), h 3,0–3,5 м | C71: шт. | D71: 155 | E71: 14000 | F71: =D71*E71 -> 2170000 | G71: посадка с комом, в т.ч. яма и подвязка
A72: 6.5 | B72: Ольха серая (Alnus incana) | C72: шт. | D72: 145 | E72: 6800 | F72: =D72*E72 -> 986000 | G72: посадка с комом, в т.ч. яма и подвязка
A73: 6.6 | B73: Черёмуха обыкновенная (Prunus padus) | C73: шт. | D73: 117 | E73: 5900 | F73: =D73*E73 -> 690300 | G73: посадка с комом, в т.ч. яма и подвязка
A74: 6.7 | B74: Сосна кедровая сибирская (Pinus sibirica), h 2–2,5 м | C74: шт. | D74: 88 | E74: 18500 | F74: =D74*E74 -> 1628000 | G74: посадка с комом, в т.ч. яма и подвязка
A75: 6.8 | B75: Ива козья и пятитычинковая (Salix caprea, S. pentandra) | C75: шт. | D75: 84 | E75: 5600 | F75: =D75*E75 -> 470400 | G75: посадка с комом, в т.ч. яма и подвязка
A76: 6.9 | B76: Лиственница сибирская (Larix sibirica) | C76: шт. | D76: 49 | E76: 11000 | F76: =D76*E76 -> 539000 | G76: посадка с комом, в т.ч. яма и подвязка
A77: 6.10 | B77: Рябина обыкновенная (Sorbus aucuparia) | C77: шт. | D77: 49 | E77: 5800 | F77: =D77*E77 -> 284200 | G77: посадка с комом, в т.ч. яма и подвязка
A78: 6.11 | B78: Кустарники в куртинах (дерен белый, спирея, шиповник морщинистый, ива, можжевельник) | C78: шт. | D78: 1680 | E78: 2150 | F78: =D78*E78 -> 3612000 | G78: 168 куртин по 12 м², 10 шт/куртину
A79: 6.12 | B79: Живая изгородь (дерен белый) | C79: м | D79: 420 | E79: 4800 | F79: =D79*E79 -> 2016000
A80: 6.13 | B80: Многолетники: сад опылителей, цветники у входа и детской зоны | C80: м² | D80: 985.8 | E80: 3400 | F80: =D80*E80 -> 3351720
A81: 6.14 | B81: Прибрежная полоса 4 м: влаголюбивые многолетники и осоки | C81: м² | D81: 3528 | E81: 380 | F81: =D81*E81 -> 1340640 | G81: по документации: 3–5 м
A82: 6.15 | B82: Газон посевной | C82: м² | D82: 21834.5 | E82: 260 | F82: =D82*E82 -> 5676970
A83: 6.16 | B83: Луг (разнотравье местных видов) | C83: м² | D83: 38321.5 | E83: 95 | F83: =D83*E83 -> 3640542.5
A84: 6.17 | B84: Растительный грунт: торфо-песчаная смесь | C84: м³ | D84: 9420.8 | E84: 1450 | F84: =D84*E84 -> 13660160 | G84: газон 0,2 м; цветники 0,4 м; ямы 1,5 м³; биоканавы 0,5 м
A85: 6.18 | B85: Автоматический полив газонов и цветников | C85: м² | D85: 22820.2 | E85: 520 | F85: =D85*E85 -> 11866504
A86: 6.19 | B86: Гарантийный уход за посадками 24 мес. | C86: шт. | D86: 3583 | E86: 600 | F86: =D86*E86 -> 2149800
A87: 6.20 | B87: Берёза карликовая (ерник, Betula nana) в группах-стланцах | C87: шт. | D87: 497 | E87: 1400 | F87: =D87*E87 -> 695800 | G87: 72 групп по 5–9 шт.
A88: 6.21 | B88: Стланиковые формы берёзы пушистой, крупномерные, с формировкой кроны | C88: шт. | D88: 23 | E88: 22000 | F88: =D88*E88 -> 506000 | G88: у воды, у фигур и станции
B89: Итого по разделу | F89: =SUM(F68:F88) -> 60630636
A91: 7 | B91: Ливневая система и биоинженерия
A92: 7.1 | B92: Биоканавы (шир. 3 м, фильтрующая загрузка) | C92: м | D92: 975.2 | E92: 5600 | F92: =D92*E92 -> 5461120 | G92: по документации ≥ 2 м
A93: 7.2 | B93: Дождевые сады | C93: м² | D93: 515.5 | E93: 7200 | F93: =D93*E93 -> 3711600 | G93: 6 шт.
A94: 7.3 | B94: Водопропуски и перетоки Ø400 | C94: шт. | D94: 12 | E94: 62000 | F94: =D94*E94 -> 744000
A95: 7.4 | B95: Дренаж вдоль аллей (труба Ø110 в геотекстиле, песчаная подушка) | C95: м | D95: 1107.3 | E95: 2100 | F95: =D95*E95 -> 2325330 | G95: по документации
B96: Итого по разделу | F96: =SUM(F92:F95) -> 12242050
A98: 8 | B98: Инженерные сети и освещение
A99: 8.1 | B99: Электроснабжение: КТП, ВРУ, подключение | C99: компл. | D99: 1 | E99: 6400000 | F99: =D99*E99 -> 6400000
A100: 8.2 | B100: Кабельные линии освещения в траншее | C100: м | D100: 2294.1 | E100: 1350 | F100: =D100*E100 -> 3097035
A101: 8.3 | B101: Опоры освещения LED H = 4 м | C101: шт. | D101: 97 | E101: 38500 | F101: =D101*E101 -> 3734500
A102: 8.4 | B102: Подсветка башни, пирсов и каскада | C102: компл. | D102: 1 | E102: 1200000 | F102: =D102*E102 -> 1200000
A103: 8.5 | B103: Водопровод В1 и канализация К1 к павильонам-туалетам, ресторану и киоскам | C103: м | D103: 645 | E103: 5900 | F103: =D103*E103 -> 3805500 | G103: в т. ч. греющий кабель и утепление труб (промерзание)
A104: 8.6 | B104: Видеонаблюдение и Wi-Fi | C104: шт. | D104: 12 | E104: 96000 | F104: =D104*E104 -> 1152000 | G104: опоры с камерами
A105: 8.7 | B105: Локальные канализационные насосные станции (низкие отметки бывшего болота) | C105: шт. | D105: 2 | E105: 2600000 | F105: =D105*E105 -> 5200000 | G105: по результатам изысканий
A106: 8.8 | B106: Электроснабжение ресторана и павильонов: кабели, щиты, учёт | C106: компл. | D106: 1 | E106: 3400000 | F106: =D106*E106 -> 3400000 | G106: отопление павильонов круглый год
B107: Итого по разделу | F107: =SUM(F99:F106) -> 27989035
...
